nbdev_test/__init__.py
nbdev_test/_nbdev.py
nbdev_test/core.py
nbdev_test-0.0.1.dist-info/LICENSE
nbdev_test-0.0.1.dist-info/METADATA
nbdev_test-0.0.1.dist-info/WHEEL
nbdev_test-0.0.1.dist-info/entry_points.txt
nbdev_test-0.0.1.dist-info/top_level.txt
nbdev_test-0.0.1.dist-info/RECORD
