Metadata-Version: 2.1
Name: nbdev-test
Version: 0.0.1
Summary: I am testing nbdev from fastai
Home-page: https://github.com/phucnsp/nbdev_test
Author: phuc su
Author-email: phucnsp@gmail.com
License: Apache Software License 2.0
Keywords: abc123
Platform: UNKNOWN
Classifier: Development Status :: 3 - Alpha
Classifier: Intended Audience :: Developers
Classifier: License :: OSI Approved :: Apache Software License
Classifier: Natural Language :: English
Classifier: Programming Language :: Python :: 3.6
Classifier: Programming Language :: Python :: 3.7
Classifier: Programming Language :: Python :: 3.8
Requires-Python: >=3.6
